README.md
setup.py
faq_migrations/__init__.py
faq_migrations/cli.py
faq_migrations/manager.py
faq_migrations/patch.py
faq_migrations/settings.py
faq_migrations/test.py
faq_migrations.egg-info/PKG-INFO
faq_migrations.egg-info/SOURCES.txt
faq_migrations.egg-info/dependency_links.txt
faq_migrations.egg-info/entry_points.txt
faq_migrations.egg-info/requires.txt
faq_migrations.egg-info/top_level.txt
faq_migrations/models/__init__.py
faq_migrations/models/history.py
faq_migrations/source/__init__.py
faq_migrations/source/alembic_wrapper.py
faq_migrations/tests/__init__.py
faq_migrations/tests/database.py
faq_migrations/tests/database_test.py
faq_migrations/tests/utils.py