Metadata-Version: 1.0
Name: faq-migrations
Version: 1.0.25
Summary: UNKNOWN
Home-page: UNKNOWN
Author: Maksym Stukalo
Author-email: stukalo.maksym@gmail.com
License: UNKNOWN
Platform: UNKNOWN
